Workbook

Sheet Données
A1: SUIVI MENSUEL DES INDICATEURS — 5 ANS
A2: Indicateur | B2: Unité | C2: 2022 | O2: 2023 | AA2: 2024 | AM2: 2025 | AY2: 2026
C3: Jan | D3: Fév | E3: Mar | F3: Avr | G3: Mai | H3: Jun | I3: Jul | J3: Aoû | K3: Sep | L3: Oct | M3: Nov | N3: Déc | O3: Jan | P3: Fév | Q3: Mar | R3: Avr | S3: Mai | T3: Jun | U3: Jul | V3: Aoû | W3: Sep | X3: Oct | Y3: Nov | Z3: Déc | AA3: Jan | AB3: Fév | AC3: Mar | AD3: Avr | AE3: Mai | AF3: Jun | AG3: Jul | AH3: Aoû | AI3: Sep | AJ3: Oct | AK3: Nov | AL3: Déc | AM3: Jan | AN3: Fév | AO3: Mar | AP3: Avr | AQ3: Mai | AR3: Jun | AS3: Jul | AT3: Aoû | AU3: Sep | AV3: Oct | AW3: Nov | AX3: Déc | AY3: Jan | AZ3: Fév | BA3: Mar | BB3: Avr | BC3: Mai | BD3: Jun | BE3: Jul | BF3: Aoû | BG3: Sep | BH3: Oct | BI3: Nov | BJ3: Déc
A4: MARCHÉS BOURSIERS
A5: CAC 40 | B5: points | C5: 6862 | D5: 6659 | E5: 6685 | F5: 6361 | G5: 6362 | H5: 5922 | I5: 6411 | J5: 6192 | K5: 5765 | L5: 6268 | M5: 6684 | N5: 6474 | O5: 7088 | P5: 7270 | Q5: 7322 | R5: 7491 | S5: 7323 | T5: 7400 | U5: 7476 | V5: 7309 | W5: 7135 | X5: 6885 | Y5: 7250 | Z5: 7543 | AA5: 7618 | AB5: 7932 | AC5: 8206 | AD5: 8023 | AE5: 8094 | AF5: 7558 | AG5: 7688 | AH5: 7646 | AI5: 7635 | AJ5: 7350 | AK5: 7235 | AL5: 7380 | AM5: 7988 | AN5: 8118 | AO5: 7936 | AP5: 7507 | AQ5: 7953 | AR5: 7814 | AS5: 7780 | AT5: 7550 | AU5: 7600 | AV5: 7490 | AW5: 7350 | AX5: 7260 | AY5: 8130 | AZ5: 8207 | BA5: 7901 | BB5: 8114 | BC5: 8116
A6: Euro Stoxx 50 | B6: points | C6: 4173 | D6: 4062 | E6: 3901 | F6: 3756 | G6: 3723 | H6: 3454 | I6: 3612 | J6: 3506 | K6: 3252 | L6: 3617 | M6: 3907 | N6: 3793 | O6: 4216 | P6: 4267 | Q6: 4316 | R6: 4359 | S6: 4261 | T6: 4399 | U6: 4409 | V6: 4249 | W6: 4094 | X6: 3995 | Y6: 4381 | Z6: 4521 | AA6: 4683 | AB6: 4918 | AC6: 5083 | AD6: 4929 | AE6: 5004 | AF6: 4848 | AG6: 4934 | AH6: 4942 | AI6: 4958 | AJ6: 4844 | AK6: 4839 | AL6: 4896 | AM6: 5262 | AN6: 5513 | AO6: 5359 | AP6: 5106 | AQ6: 5354 | AR6: 5227 | AS6: 5180 | AT6: 5050 | AU6: 5100 | AV6: 5020 | AW6: 4940 | AX6: 4880 | AY6: 5380 | AZ6: 5550 | BA6: 5290 | BB6: 5720 | BC6: 5981
A7: Nasdaq Composite | B7: points | C7: 14239 | D7: 13751 | E7: 14262 | F7: 12335 | G7: 11835 | H7: 10774 | I7: 12391 | J7: 11630 | K7: 10575 | L7: 10971 | M7: 11468 | N7: 10939 | O7: 11621 | P7: 11455 | Q7: 12222 | R7: 12227 | S7: 13181 | T7: 13788 | U7: 14317 | V7: 13791 | W7: 13219 | X7: 12851 | Y7: 14226 | Z7: 15011 | AA7: 15361 | AB7: 15997 | AC7: 16380 | AD7: 15657 | AE7: 16736 | AF7: 17733 | AG7: 17599 | AH7: 17713 | AI7: 17926 | AJ7: 18096 | AK7: 19218 | AL7: 19310 | AM7: 19281 | AN7: 18847 | AO7: 17300 | AP7: 17166 | AQ7: 19113 | AR7: 20058 | AS7: 20453 | AT7: 19474 | AU7: 19791 | AV7: 18518 | AW7: 19161 | AX7: 19311 | AY7: 19956 | AZ7: 19630 | BA7: 17899 | BB7: 19088 | BC7: 26121
A8: Dow Jones | B8: points | C8: 35132 | D8: 33893 | E8: 34678 | F8: 32977 | G8: 32990 | H8: 30775 | I8: 32845 | J8: 31510 | K8: 28726 | L8: 32732 | M8: 34589 | N8: 33147 | O8: 34086 | P8: 32657 | Q8: 33274 | R8: 34098 | S8: 32909 | T8: 34408 | U8: 35559 | V8: 34722 | W8: 33507 | X8: 33052 | Y8: 35950 | Z8: 37690 | AA8: 38150 | AB8: 38997 | AC8: 39807 | AD8: 37816 | AE8: 38687 | AF8: 39118 | AG8: 40842 | AH8: 41563 | AI8: 42330 | AJ8: 41763 | AK8: 44910 | AL8: 42544 | AM8: 44544 | AN8: 43841 | AO8: 41583 | AP8: 40669 | AQ8: 44114 | AR8: 44271 | AS8: 44765 | AT8: 41563 | AU8: 42348 | AV8: 41763 | AW8: 44538 | AX8: 42573 | AY8: 45003 | AZ8: 43840 | BA8: 41582 | BB8: 40527 | BC8: 49878
A9: VIX — Volatilité | B9: index | C9: 24.8 | D9: 30.7 | E9: 22.5 | F9: 33.4 | G9: 26.2 | H9: 28.7 | I9: 21.3 | J9: 25.5 | K9: 31.6 | L9: 25.9 | M9: 20.6 | N9: 21.7 | O9: 18.4 | P9: 20.7 | Q9: 18.7 | R9: 15.8 | S9: 17 | T9: 13.6 | U9: 13.3 | V9: 15.7 | W9: 17.5 | X9: 19.7 | Y9: 12.6 | Z9: 12.5 | AA9: 13.3 | AB9: 13.1 | AC9: 13 | AD9: 15.3 | AE9: 13.4 | AF9: 12.4 | AG9: 16.4 | AH9: 15 | AI9: 16.7 | AJ9: 23.2 | AK9: 14.1 | AL9: 17.4 | AM9: 16.4 | AN9: 19.6 | AO9: 22.3 | AP9: 34.5 | AQ9: 18.2 | AR9: 16.7 | AS9: 16 | AT9: 20.1 | AU9: 17.3 | AV9: 22.4 | AW9: 15.6 | AX9: 18 | AY9: 16.1 | AZ9: 20.4 | BA9: 21.9 | BB9: 24.8 | BC9: 17.4
A10: EUR / USD | B10: taux | C10: 1.1231 | D10: 1.1121 | E10: 1.1074 | F10: 1.0544 | G10: 1.0736 | H10: 1.0484 | I10: 1.0217 | J10: 1.0001 | K10: 0.9798 | L10: 0.9982 | M10: 1.0352 | N10: 1.0698 | O10: 1.0861 | P10: 1.0582 | Q10: 1.0927 | R10: 1.1021 | S10: 1.0746 | T10: 1.0912 | U10: 1.1008 | V10: 1.084 | W10: 1.0568 | X10: 1.0557 | Y10: 1.0888 | Z10: 1.105 | AA10: 1.0845 | AB10: 1.0843 | AC10: 1.0793 | AD10: 1.0726 | AE10: 1.0853 | AF10: 1.0715 | AG10: 1.0815 | AH10: 1.1046 | AI10: 1.1143 | AJ10: 1.0871 | AK10: 1.0534 | AL10: 1.0352 | AM10: 1.0308 | AN10: 1.0387 | AO10: 1.0817 | AP10: 1.1382 | AQ10: 1.1318 | AR10: 1.1283 | AS10: 1.105 | AT10: 1.0981 | AU10: 1.1037 | AV10: 1.0902 | AW10: 1.053 | AX10: 1.0352 | AY10: 1.0301 | AZ10: 1.0488 | BA10: 1.0838 | BB10: 1.1357 | BC10: 1.128
A11: OAT 10 ans | B11: % | C11: 0.3 | D11: 0.76 | E11: 0.96 | F11: 1.43 | G11: 1.63 | H11: 2.07 | I11: 1.65 | J11: 1.91 | K11: 2.74 | L11: 2.83 | M11: 2.52 | N11: 3.12 | O11: 2.87 | P11: 3.24 | Q11: 3.02 | R11: 3.01 | S11: 3.21 | T11: 3.43 | U11: 3.4 | V11: 3.54 | W11: 3.85 | X11: 3.84 | Y11: 3.42 | Z11: 3.15 | AA11: 3.27 | AB11: 3.42 | AC11: 3.16 | AD11: 3.39 | AE11: 3.22 | AF11: 3.34 | AG11: 3.22 | AH11: 3.02 | AI11: 3 | AJ11: 3.25 | AK11: 3.2 | AL11: 3.3 | AM11: 3.41 | AN11: 3.52 | AO11: 3.75 | AP11: 3.69 | AQ11: 3.62 | AR11: 3.58 | AS11: 3.51 | AT11: 3.42 | AU11: 3.38 | AV11: 3.32 | AW11: 3.28 | AX11: 3.2 | AY11: 3.4 | AZ11: 3.48 | BA11: 3.72 | BB11: 3.63 | BC11: 3.55
A12: Brent (USD/baril) | B12: USD | C12: 91.2 | D12: 98 | E12: 112 | F12: 107.5 | G12: 122.8 | H12: 114.7 | I12: 105.8 | J12: 100 | K12: 88.5 | L12: 96.2 | M12: 85.4 | N12: 82.7 | O12: 84.9 | P12: 83 | Q12: 79.8 | R12: 79.5 | S12: 74.3 | T12: 74.9 | U12: 85.6 | V12: 86.3 | W12: 93 | X12: 87.3 | Y12: 80 | Z12: 77 | AA12: 82.4 | AB12: 82 | AC12: 87.5 | AD12: 88.4 | AE12: 82.5 | AF12: 85 | AG12: 80.7 | AH12: 78.8 | AI12: 72 | AJ12: 73.2 | AK12: 73.5 | AL12: 74.7 | AM12: 76.8 | AN12: 74.5 | AO12: 73.5 | AP12: 67 | AQ12: 61.2 | AR12: 67.8 | AS12: 78.5 | AT12: 75.6 | AU12: 71.2 | AV12: 73.4 | AW12: 71 | AX12: 73.5 | AY12: 76.2 | AZ12: 74.4 | BA12: 72.1 | BB12: 69.5 | BC12: 68.3
A14: INDICATEURS ÉCONOMIQUES
A15: SMIC horaire brut | B15: € | C15: 10.57 | D15: 10.57 | E15: 10.57 | F15: 10.57 | G15: 10.85 | H15: 10.85 | I15: 10.85 | J15: 10.85 | K15: 10.93 | L15: 10.93 | M15: 10.93 | N15: 10.93 | O15: 11.27 | P15: 11.27 | Q15: 11.27 | R15: 11.27 | S15: 11.52 | T15: 11.52 | U15: 11.52 | V15: 11.52 | W15: 11.52 | X15: 11.52 | Y15: 11.52 | Z15: 11.52 | AA15: 11.65 | AB15: 11.65 | AC15: 11.65 | AD15: 11.65 | AE15: 11.65 | AF15: 11.65 | AG15: 11.65 | AH15: 11.65 | AI15: 11.65 | AJ15: 11.65 | AK15: 11.88 | AL15: 11.88 | AM15: 11.88 | AN15: 11.88 | AO15: 11.88 | AP15: 11.88 | AQ15: 11.88 | AR15: 11.88 | AS15: 11.88 | AT15: 11.88 | AU15: 11.88 | AV15: 11.88 | AW15: 11.88 | AX15: 11.88 | AY15: 11.88 | AZ15: 11.88 | BA15: 11.88 | BB15: 11.88 | BC15: 11.88
A16: Taux directeur BCE | B16: % | C16: -0.5 | D16: -0.5 | E16: -0.5 | F16: -0.5 | G16: -0.5 | H16: -0.5 | I16: 0 | J16: 0 | K16: 0.75 | L16: 0.75 | M16: 1.5 | N16: 2 | O16: 2 | P16: 2.5 | Q16: 3 | R16: 3.25 | S16: 3.25 | T16: 3.5 | U16: 3.75 | V16: 3.75 | W16: 4 | X16: 4 | Y16: 4 | Z16: 4 | AA16: 4 | AB16: 4 | AC16: 4 | AD16: 4 | AE16: 4 | AF16: 3.75 | AG16: 3.75 | AH16: 3.75 | AI16: 3.5 | AJ16: 3.25 | AK16: 3 | AL16: 3 | AM16: 2.75 | AN16: 2.75 | AO16: 2.5 | AP16: 2.5 | AQ16: 2.25 | AR16: 2.25 | AS16: 2 | AT16: 2 | AU16: 1.75 | AV16: 1.75 | AW16: 1.5 | AX16: 1.5 | AY16: 1.5 | AZ16: 1.5 | BA16: 1.5 | BB16: 2.25 | BC16: 2.25
A17: Inflation France (IPC) | B17: % | C17: 2.9 | D17: 3.6 | E17: 4.5 | F17: 4.8 | G17: 5.2 | H17: 5.8 | I17: 6.1 | J17: 5.9 | K17: 5.6 | L17: 6.2 | M17: 6.2 | N17: 5.9 | O17: 6 | P17: 6.2 | Q17: 5.6 | R17: 5.9 | S17: 5.1 | T17: 4.5 | U17: 4.3 | V17: 4.9 | W17: 4.9 | X17: 4 | Y17: 3.5 | Z17: 3.7 | AA17: 3.1 | AB17: 3 | AC17: 2.3 | AD17: 2.2 | AE17: 2.3 | AF17: 2.2 | AG17: 2.3 | AH17: 2.2 | AI17: 1.4 | AJ17: 1.2 | AK17: 1.3 | AL17: 1.3 | AM17: 1.8 | AN17: 0.9 | AO17: 0.8 | AP17: 0.8 | AQ17: 0.7 | AR17: 1 | AS17: 1 | AT17: 1.2 | AU17: 1.1 | AV17: 1.2 | AW17: 1 | AX17: 1.3 | AY17: 0.8 | AZ17: 0.9 | BA17: 0.8 | BB17: 0.7
A18: Chômage France (BIT) | B18: % | C18: 7.4 | D18: 7.4 | E18: 7.4 | F18: 7.3 | G18: 7.3 | H18: 7.3 | I18: 7.3 | J18: 7.3 | K18: 7.3 | L18: 7.2 | M18: 7.2 | N18: 7.2 | O18: 7.1 | P18: 7.1 | Q18: 7.1 | R18: 7.3 | S18: 7.3 | T18: 7.3 | U18: 7.4 | V18: 7.4 | W18: 7.4 | X18: 7.5 | Y18: 7.5 | Z18: 7.5 | AA18: 7.3 | AB18: 7.3 | AC18: 7.3 | AD18: 7.3 | AE18: 7.3 | AF18: 7.3 | AG18: 7.4 | AH18: 7.4 | AI18: 7.4 | AJ18: 7.3 | AK18: 7.3 | AL18: 7.3 | AM18: 7.4 | AN18: 7.4 | AO18: 7.4 | AP18: 7.5 | AQ18: 7.5 | AR18: 7.5 | AS18: 7.5 | AT18: 7.5 | AU18: 7.5 | AV18: 7.4 | AW18: 7.4 | AX18: 7.4 | AY18: 7.3 | AZ18: 7.3 | BA18: 7.3 | BB18: 7.3 | BC18: 7.3
A19: Pass Navigo mensuel | B19: € | C19: 75.2 | D19: 75.2 | E19: 75.2 | F19: 75.2 | G19: 75.2 | H19: 75.2 | I19: 75.2 | J19: 75.2 | K19: 75.2 | L19: 75.2 | M19: 75.2 | N19: 75.2 | O19: 84.1 | P19: 84.1 | Q19: 84.1 | R19: 84.1 | S19: 84.1 | T19: 84.1 | U19: 84.1 | V19: 84.1 | W19: 84.1 | X19: 84.1 | Y19: 84.1 | Z19: 84.1 | AA19: 86.4 | AB19: 86.4 | AC19: 86.4 | AD19: 86.4 | AE19: 86.4 | AF19: 86.4 | AG19: 86.4 | AH19: 86.4 | AI19: 86.4 | AJ19: 86.4 | AK19: 86.4 | AL19: 86.4 | AM19: 88.8 | AN19: 88.8 | AO19: 88.8 | AP19: 88.8 | AQ19: 88.8 | AR19: 88.8 | AS19: 88.8 | AT19: 88.8 | AU19: 88.8 | AV19: 88.8 | AW19: 88.8 | AX19: 88.8 | AY19: 88.8 | AZ19: 88.8 | BA19: 88.8 | BB19: 88.8 | BC19: 88.8
A20: Baguette — prix moyen | B20: € | C20: 0.9 | D20: 0.9 | E20: 0.93 | F20: 0.93 | G20: 0.95 | H20: 0.98 | I20: 0.99 | J20: 1.01 | K20: 1.05 | L20: 1.07 | M20: 1.09 | N20: 1.1 | O20: 1.13 | P20: 1.15 | Q20: 1.16 | R20: 1.17 | S20: 1.18 | T20: 1.18 | U20: 1.19 | V20: 1.19 | W20: 1.19 | X20: 1.2 | Y20: 1.2 | Z20: 1.2 | AA20: 1.2 | AB20: 1.2 | AC20: 1.2 | AD20: 1.21 | AE20: 1.21 | AF20: 1.21 | AG20: 1.22 | AH20: 1.22 | AI20: 1.22 | AJ20: 1.22 | AK20: 1.22 | AL20: 1.22 | AM20: 1.23 | AN20: 1.23 | AO20: 1.23 | AP20: 1.23 | AQ20: 1.23 | AR20: 1.23 | AS20: 1.23 | AT20: 1.23 | AU20: 1.23 | AV20: 1.24 | AW20: 1.24 | AX20: 1.24 | AY20: 1.24 | AZ20: 1.24 | BA20: 1.24 | BB20: 1.25 | BC20: 1.25
A21: Déficit public / PIB | B21: % PIB | C21: -4.8 | D21: -4.8 | E21: -4.8 | F21: -4.8 | G21: -4.8 | H21: -4.8 | I21: -4.8 | J21: -4.8 | K21: -4.8 | L21: -4.8 | M21: -4.8 | N21: -4.8 | O21: -5.5 | P21: -5.5 | Q21: -5.5 | R21: -5.5 | S21: -5.5 | T21: -5.5 | U21: -5.5 | V21: -5.5 | W21: -5.5 | X21: -5.5 | Y21: -5.5 | Z21: -5.5 | AA21: -6.1 | AB21: -6.1 | AC21: -6.1 | AD21: -6.1 | AE21: -6.1 | AF21: -6.1 | AG21: -6.1 | AH21: -6.1 | AI21: -6.1 | AJ21: -6.1 | AK21: -6.1 | AL21: -6.1 | AM21: -5.8 | AN21: -5.8 | AO21: -5.8 | AP21: -5.8 | AQ21: -5.8 | AR21: -5.8 | AS21: -5.8 | AT21: -5.8 | AU21: -5.8 | AV21: -5.8 | AW21: -5.8 | AX21: -5.8 | AY21: -5.8 | AZ21: -5.8 | BA21: -5.8 | BB21: -5.8 | BC21: -5.8
A22: Confiance ménages INSEE | B22: index | C22: 99 | D22: 96 | E22: 91 | F22: 88 | G22: 88 | H22: 82 | I22: 80 | J22: 82 | K22: 79 | L22: 82 | M22: 83 | N22: 82 | O22: 80 | P22: 81 | Q22: 82 | R22: 84 | S22: 83 | T22: 84 | U22: 86 | V22: 86 | W22: 84 | X22: 83 | Y22: 86 | Z22: 87 | AA22: 89 | AB22: 89 | AC22: 90 | AD22: 91 | AE22: 91 | AF22: 90 | AG22: 91 | AH22: 91 | AI22: 92 | AJ22: 93 | AK22: 94 | AL22: 92 | AM22: 91 | AN22: 91 | AO22: 90 | AP22: 89 | AQ22: 90 | AR22: 91 | AS22: 91 | AT22: 90 | AU22: 90 | AV22: 89 | AW22: 90 | AX22: 90 | AY22: 91 | AZ22: 90 | BA22: 89 | BB22: 90
A24: IMMOBILIER
A25: ICC — Coût Construction | B25: index | C25: 1948 | D25: 1948 | E25: 1948 | F25: 1966 | G25: 1966 | H25: 1966 | I25: 2037 | J25: 2037 | K25: 2037 | L25: 2052 | M25: 2052 | N25: 2052 | O25: 2077 | P25: 2077 | Q25: 2077 | R25: 2123 | S25: 2123 | T25: 2123 | U25: 2106 | V25: 2106 | W25: 2106 | X25: 2162 | Y25: 2162 | Z25: 2162 | AA25: 2227 | AB25: 2227 | AC25: 2227 | AD25: 2205 | AE25: 2205 | AF25: 2205 | AG25: 2143 | AH25: 2143 | AI25: 2143 | AJ25: 2108 | AK25: 2108 | AL25: 2108 | AM25: 2146 | AN25: 2146 | AO25: 2146 | AP25: 2086 | AQ25: 2086 | AR25: 2086 | AS25: 2056 | AT25: 2056 | AU25: 2056 | AV25: 2058 | AW25: 2058 | AX25: 2058 | AY25: 2058 | AZ25: 2058 | BA25: 2058 | BB25: 2058 | BC25: 2058
A26: ILC — Loyers Commerciaux | B26: index | C26: 120.61 | D26: 120.61 | E26: 120.61 | F26: 123.65 | G26: 123.65 | H26: 123.65 | I26: 126.13 | J26: 126.13 | K26: 126.13 | L26: 126.05 | M26: 126.05 | N26: 126.05 | O26: 128.68 | P26: 128.68 | Q26: 128.68 | R26: 131.81 | S26: 131.81 | T26: 131.81 | U26: 133.66 | V26: 133.66 | W26: 133.66 | X26: 132.63 | Y26: 132.63 | Z26: 132.63 | AA26: 134.58 | AB26: 134.58 | AC26: 134.58 | AD26: 136.72 | AE26: 136.72 | AF26: 136.72 | AG26: 137.71 | AH26: 137.71 | AI26: 137.71 | AJ26: 135.3 | AK26: 135.3 | AL26: 135.3 | AM26: 135.87 | AN26: 135.87 | AO26: 135.87 | AP26: 136.81 | AQ26: 136.81 | AR26: 136.81 | AS26: 137.09 | AT26: 137.09 | AU26: 137.09 | AV26: 134.62 | AW26: 134.62 | AX26: 134.62 | AY26: 134.62 | AZ26: 134.62 | BA26: 134.62 | BB26: 134.62 | BC26: 134.62
A27: ILAT — Act. Tertiaires | B27: index | C27: 120.73 | D27: 120.73 | E27: 120.73 | F27: 122.65 | G27: 122.65 | H27: 122.65 | I27: 124.53 | J27: 124.53 | K27: 124.53 | L27: 126.66 | M27: 126.66 | N27: 126.66 | O27: 128.59 | P27: 128.59 | Q27: 128.59 | R27: 130.64 | S27: 130.64 | T27: 130.64 | U27: 132.15 | V27: 132.15 | W27: 132.15 | X27: 133.69 | Y27: 133.69 | Z27: 133.69 | AA27: 135.13 | AB27: 135.13 | AC27: 135.13 | AD27: 136.45 | AE27: 136.45 | AF27: 136.45 | AG27: 137.12 | AH27: 137.12 | AI27: 137.12 | AJ27: 137.29 | AK27: 137.29 | AL27: 137.29 | AM27: 137.29 | AN27: 137.29 | AO27: 137.29 | AP27: 137.15 | AQ27: 137.15 | AR27: 137.15 | AS27: 137.07 | AT27: 137.07 | AU27: 137.07 | AV27: 137.21 | AW27: 137.21 | AX27: 137.21 | AY27: 137.21 | AZ27: 137.21 | BA27: 137.21 | BB27: 137.21 | BC27: 137.21
A28: IRL — Réf. des Loyers | B28: index | C28: 133.93 | D28: 133.93 | E28: 133.93 | F28: 135.84 | G28: 135.84 | H28: 135.84 | I28: 137.93 | J28: 137.93 | K28: 137.93 | L28: 138.26 | M28: 138.26 | N28: 138.26 | O28: 140.59 | P28: 140.59 | Q28: 140.59 | R28: 142.07 | S28: 142.07 | T28: 142.07 | U28: 143.52 | V28: 143.52 | W28: 143.52 | X28: 141.48 | Y28: 141.48 | Z28: 141.48 | AA28: 142.08 | AB28: 142.08 | AC28: 142.08 | AD28: 143.54 | AE28: 143.54 | AF28: 143.54 | AG28: 144.51 | AH28: 144.51 | AI28: 144.51 | AJ28: 144.89 | AK28: 144.89 | AL28: 144.89 | AM28: 145.28 | AN28: 145.28 | AO28: 145.28 | AP28: 145.59 | AQ28: 145.59 | AR28: 145.59 | AS28: 145.62 | AT28: 145.62 | AU28: 145.62 | AV28: 145.4 | AW28: 145.4 | AX28: 145.4 | AY28: 145.4 | AZ28: 145.4 | BA28: 145.4 | BB28: 145.4 | BC28: 145.4
A29: Taux crédit immo moyen | B29: % | C29: 1.06 | D29: 1.12 | E29: 1.27 | F29: 1.4 | G29: 1.55 | H29: 1.71 | I29: 1.85 | J29: 1.97 | K29: 2.15 | L29: 2.4 | M29: 2.6 | N29: 2.75 | O29: 2.82 | P29: 2.97 | Q29: 3.04 | R29: 3.21 | S29: 3.45 | T29: 3.61 | U29: 3.82 | V29: 3.97 | W29: 4.05 | X29: 4.14 | Y29: 4.22 | Z29: 4.24 | AA29: 4.19 | AB29: 4.1 | AC29: 3.99 | AD29: 3.88 | AE29: 3.79 | AF29: 3.72 | AG29: 3.68 | AH29: 3.6 | AI29: 3.55 | AJ29: 3.5 | AK29: 3.45 | AL29: 3.38 | AM29: 3.34 | AN29: 3.3 | AO29: 3.28 | AP29: 3.25 | AQ29: 3.22 | AR29: 3.18 | AS29: 3.12 | AT29: 3.1 | AU29: 3.07 | AV29: 3.05 | AW29: 3.02 | AX29: 3 | AY29: 2.98 | AZ29: 2.95 | BA29: 2.92 | BB29: 2.9 | BC29: 2.88
A30: Transactions (12 mois) | B30: milliers | C30: 1150 | D30: 1140 | E30: 1130 | F30: 1120 | G30: 1110 | H30: 1090 | I30: 1070 | J30: 1050 | K30: 1020 | L30: 1000 | M30: 980 | N30: 960 | O30: 940 | P30: 915 | Q30: 895 | R30: 870 | S30: 850 | T30: 830 | U30: 820 | V30: 800 | W30: 790 | X30: 780 | Y30: 770 | Z30: 760 | AA30: 750 | AB30: 740 | AC30: 735 | AD30: 730 | AE30: 728 | AF30: 730 | AG30: 735 | AH30: 740 | AI30: 745 | AJ30: 750 | AK30: 755 | AL30: 760 | AM30: 762 | AN30: 763 | AO30: 762 | AP30: 765 | AQ30: 768 | AR30: 775 | AS30: 780 | AT30: 785 | AU30: 790 | AV30: 795 | AW30: 800 | AX30: 805 | AY30: 810 | AZ30: 815 | BA30: 818 | BB30: 820
A32: Texte bleu = cellule de saisie. Saisir en début de mois la valeur du mois précédent. Indices trimestriels (ICC, ILC, ILAT, IRL) : reporter la dernière valeur publiée sur les 3 mois du trimestre.
A35: ÉNERGIE
A36: SMIC mensuel brut | B36: €/mois | C36: =IF(C15<>"",ROUND(C15*151.67,2),"") -> 1603.15 | D36: =IF(D15<>"",ROUND(D15*151.67,2),"") -> 1603.15 | E36: =IF(E15<>"",ROUND(E15*151.67,2),"") -> 1603.15 | F36: =IF(F15<>"",ROUND(F15*151.67,2),"") -> 1603.15 | G36: =IF(G15<>"",ROUND(G15*151.67,2),"") -> 1645.62 | H36: =IF(H15<>"",ROUND(H15*151.67,2),"") -> 1645.62 | I36: =IF(I15<>"",ROUND(I15*151.67,2),"") -> 1645.62 | J36: =IF(J15<>"",ROUND(J15*151.67,2),"") -> 1645.62 | ... BC36: =IF(BC15<>"",ROUND(BC15*151.67,2),"") -> 1801.84
A37: Tarif EDF réglementé (Base 6kVA) | B37: €/kWh | C37: 0.174 | D37: 0.174 | E37: 0.174 | F37: 0.174 | G37: 0.174 | H37: 0.174 | I37: 0.174 | J37: 0.1796 | K37: 0.1796 | L37: 0.1796 | M37: 0.1796 | N37: 0.1796 | O37: 0.1796 | P37: 0.1796 | Q37: 0.1796 | R37: 0.1796 | S37: 0.1796 | T37: 0.1796 | U37: 0.1796 | V37: 0.2265 | W37: 0.2265 | X37: 0.2265 | Y37: 0.2265 | Z37: 0.2265 | AA37: 0.2265 | AB37: 0.2265 | AC37: 0.2459 | AD37: 0.2459 | AE37: 0.2459 | AF37: 0.2459 | AG37: 0.2459 | AH37: 0.2459 | AI37: 0.2516 | AJ37: 0.2516 | AK37: 0.2516 | AL37: 0.2516 | AM37: 0.2516 | AN37: 0.2645 | AO37: 0.2645 | AP37: 0.2645 | AQ37: 0.2645 | AR37: 0.2645 | AS37: 0.2645 | AT37: 0.2645 | AU37: 0.2645 | AV37: 0.2645 | AW37: 0.2645 | AX37: 0.2645 | AY37: 0.2645 | AZ37: 0.2645 | BA37: 0.2645 | BB37: 0.2645 | BC37: 0.2645
A38: Gaz naturel — prix réf. CRE | B38: €/MWh | C38: 81 | D38: 90 | E38: 105 | F38: 108 | G38: 115 | H38: 118 | I38: 120.5 | J38: 154 | K38: 168 | L38: 130 | M38: 115 | N38: 104 | O38: 98 | P38: 92 | Q38: 85 | R38: 78 | S38: 72 | T38: 65 | U38: 57 | V38: 56 | W38: 54 | X38: 58 | Y38: 62 | Z38: 65 | AA38: 63 | AB38: 61 | AC38: 59 | AD38: 57 | AE38: 55 | AF38: 54 | AG38: 52 | AH38: 50 | AI38: 48 | AJ38: 49 | AK38: 52 | AL38: 54 | AM38: 57 | AN38: 62 | AO38: 65 | AP38: 63 | AQ38: 60 | AR38: 58 | AS38: 55 | AT38: 54 | AU38: 52 | AV38: 53 | AW38: 56 | AX38: 58 | AY38: 62 | AZ38: 64 | BA38: 63 | BB38: 61 | BC38: 60
A39: Taux Livret A | B39: % | C39: 0.5 | D39: 1 | E39: 1 | F39: 1 | G39: 1 | H39: 1 | I39: 1 | J39: 2 | K39: 2 | L39: 2 | M39: 2 | N39: 2 | O39: 2 | P39: 3 | Q39: 3 | R39: 3 | S39: 3 | T39: 3 | U39: 3 | V39: 3 | W39: 3 | X39: 3 | Y39: 3 | Z39: 3 | AA39: 3 | AB39: 3 | AC39: 3 | AD39: 3 | AE39: 3 | AF39: 3 | AG39: 3 | AH39: 3 | AI39: 3 | AJ39: 3 | AK39: 3 | AL39: 3 | AM39: 3 | AN39: 2.4 | AO39: 2.4 | AP39: 2.4 | AQ39: 2.4 | AR39: 2.4 | AS39: 2.4 | AT39: 1.7 | AU39: 1.7 | AV39: 1.7 | AW39: 1.7 | AX39: 1.7 | AY39: 1.7 | AZ39: 1.7 | BA39: 1.7 | BB39: 1.7 | BC39: 1.7
A40: Légende couleurs : VERT PÂLE = donnée vérifiée source officielle | JAUNE PÂLE = estimation issue de données publiques | VIOLET PÂLE = donnée trimestrielle répétée sur 3 mois | BLEU PÂLE = formule liée à un autre indicateur

Sheet Tableau de bord
A1: TABLEAU DE BORD — DERNIÈRES VALEURS & ÉVOLUTIONS
A2: Calculé automatiquement depuis la feuille Données. Valeurs issues de la dernière cellule renseignée de chaque indicateur.
A3: Indicateur | B3: Unité | C3: Dernière valeur | D3: vs mois préc. | E3: vs 6 mois | F3: vs 1 an | G3: vs 2 ans | H3: Source
A4: MARCHÉS BOURSIERS
A5: CAC 40 | B5: points | C5: =IFERROR(LOOKUP(2,1/(Données!C5:BL5<>""),Données!C5:BL5),"") -> 8116 | D5: =IFERROR(LOOKUP(2,1/(Données!C5:BL5<>""),Données!C5:BL5)-INDEX(Données!C5:BL5,MATCH(2,1/(Données!C5:BL5<>""),0)-1+1),"") | E5: =IFERROR(LOOKUP(2,1/(Données!C5:BL5<>""),Données!C5:BL5)-INDEX(Données!C5:BL5,MATCH(2,1/(Données!C5:BL5<>""),0)-6+1),"") | F5: =IFERROR(LOOKUP(2,1/(Données!C5:BL5<>""),Données!C5:BL5)-INDEX(Données!C5:BL5,MATCH(2,1/(Données!C5:BL5<>""),0)-12+1),"") | G5: =IFERROR(LOOKUP(2,1/(Données!C5:BL5<>""),Données!C5:BL5)-INDEX(Données!C5:BL5,MATCH(2,1/(Données!C5:BL5<>""),0)-24+1),"") | H5: Yahoo Finance
A6: Euro Stoxx 50 | B6: points | C6: =IFERROR(LOOKUP(2,1/(Données!C6:BL6<>""),Données!C6:BL6),"") -> 5981 | D6: =IFERROR(LOOKUP(2,1/(Données!C6:BL6<>""),Données!C6:BL6)-INDEX(Données!C6:BL6,MATCH(2,1/(Données!C6:BL6<>""),0)-1+1),"") | E6: =IFERROR(LOOKUP(2,1/(Données!C6:BL6<>""),Données!C6:BL6)-INDEX(Données!C6:BL6,MATCH(2,1/(Données!C6:BL6<>""),0)-6+1),"") | F6: =IFERROR(LOOKUP(2,1/(Données!C6:BL6<>""),Données!C6:BL6)-INDEX(Données!C6:BL6,MATCH(2,1/(Données!C6:BL6<>""),0)-12+1),"") | G6: =IFERROR(LOOKUP(2,1/(Données!C6:BL6<>""),Données!C6:BL6)-INDEX(Données!C6:BL6,MATCH(2,1/(Données!C6:BL6<>""),0)-24+1),"") | H6: Yahoo Finance
A7: Nasdaq Composite | B7: points | C7: =IFERROR(LOOKUP(2,1/(Données!C7:BL7<>""),Données!C7:BL7),"") -> 26121 | D7: =IFERROR(LOOKUP(2,1/(Données!C7:BL7<>""),Données!C7:BL7)-INDEX(Données!C7:BL7,MATCH(2,1/(Données!C7:BL7<>""),0)-1+1),"") | E7: =IFERROR(LOOKUP(2,1/(Données!C7:BL7<>""),Données!C7:BL7)-INDEX(Données!C7:BL7,MATCH(2,1/(Données!C7:BL7<>""),0)-6+1),"") | F7: =IFERROR(LOOKUP(2,1/(Données!C7:BL7<>""),Données!C7:BL7)-INDEX(Données!C7:BL7,MATCH(2,1/(Données!C7:BL7<>""),0)-12+1),"") | G7: =IFERROR(LOOKUP(2,1/(Données!C7:BL7<>""),Données!C7:BL7)-INDEX(Données!C7:BL7,MATCH(2,1/(Données!C7:BL7<>""),0)-24+1),"") | H7: Yahoo Finance
A8: Dow Jones | B8: points | C8: =IFERROR(LOOKUP(2,1/(Données!C8:BL8<>""),Données!C8:BL8),"") -> 49878 | D8: =IFERROR(LOOKUP(2,1/(Données!C8:BL8<>""),Données!C8:BL8)-INDEX(Données!C8:BL8,MATCH(2,1/(Données!C8:BL8<>""),0)-1+1),"") | E8: =IFERROR(LOOKUP(2,1/(Données!C8:BL8<>""),Données!C8:BL8)-INDEX(Données!C8:BL8,MATCH(2,1/(Données!C8:BL8<>""),0)-6+1),"") | F8: =IFERROR(LOOKUP(2,1/(Données!C8:BL8<>""),Données!C8:BL8)-INDEX(Données!C8:BL8,MATCH(2,1/(Données!C8:BL8<>""),0)-12+1),"") | G8: =IFERROR(LOOKUP(2,1/(Données!C8:BL8<>""),Données!C8:BL8)-INDEX(Données!C8:BL8,MATCH(2,1/(Données!C8:BL8<>""),0)-24+1),"") | H8: Yahoo Finance
A9: VIX — Volatilité | B9: index | C9: =IFERROR(LOOKUP(2,1/(Données!C9:BL9<>""),Données!C9:BL9),"") -> 17.4 | D9: =IFERROR(LOOKUP(2,1/(Données!C9:BL9<>""),Données!C9:BL9)-INDEX(Données!C9:BL9,MATCH(2,1/(Données!C9:BL9<>""),0)-1+1),"") | E9: =IFERROR(LOOKUP(2,1/(Données!C9:BL9<>""),Données!C9:BL9)-INDEX(Données!C9:BL9,MATCH(2,1/(Données!C9:BL9<>""),0)-6+1),"") | F9: =IFERROR(LOOKUP(2,1/(Données!C9:BL9<>""),Données!C9:BL9)-INDEX(Données!C9:BL9,MATCH(2,1/(Données!C9:BL9<>""),0)-12+1),"") | G9: =IFERROR(LOOKUP(2,1/(Données!C9:BL9<>""),Données!C9:BL9)-INDEX(Données!C9:BL9,MATCH(2,1/(Données!C9:BL9<>""),0)-24+1),"") | H9: CBOE
A10: EUR / USD | B10: taux | C10: =IFERROR(LOOKUP(2,1/(Données!C10:BL10<>""),Données!C10:BL10),"") -> 1.128 | D10: =IFERROR(LOOKUP(2,1/(Données!C10:BL10<>""),Données!C10:BL10)-INDEX(Données!C10:BL10,MATCH(2,1/(Données!C10:BL10<>""),0)-1+1),"") | E10: =IFERROR(LOOKUP(2,1/(Données!C10:BL10<>""),Données!C10:BL10)-INDEX(Données!C10:BL10,MATCH(2,1/(Données!C10:BL10<>""),0)-6+1),"") | F10: =IFERROR(LOOKUP(2,1/(Données!C10:BL10<>""),Données!C10:BL10)-INDEX(Données!C10:BL10,MATCH(2,1/(Données!C10:BL10<>""),0)-12+1),"") | G10: =IFERROR(LOOKUP(2,1/(Données!C10:BL10<>""),Données!C10:BL10)-INDEX(Données!C10:BL10,MATCH(2,1/(Données!C10:BL10<>""),0)-24+1),"") | H10: Yahoo Finance
A11: OAT 10 ans | B11: % | C11: =IFERROR(LOOKUP(2,1/(Données!C11:BL11<>""),Données!C11:BL11),"") -> 3.55 | D11: =IFERROR(LOOKUP(2,1/(Données!C11:BL11<>""),Données!C11:BL11)-INDEX(Données!C11:BL11,MATCH(2,1/(Données!C11:BL11<>""),0)-1+1),"") | E11: =IFERROR(LOOKUP(2,1/(Données!C11:BL11<>""),Données!C11:BL11)-INDEX(Données!C11:BL11,MATCH(2,1/(Données!C11:BL11<>""),0)-6+1),"") | F11: =IFERROR(LOOKUP(2,1/(Données!C11:BL11<>""),Données!C11:BL11)-INDEX(Données!C11:BL11,MATCH(2,1/(Données!C11:BL11<>""),0)-12+1),"") | G11: =IFERROR(LOOKUP(2,1/(Données!C11:BL11<>""),Données!C11:BL11)-INDEX(Données!C11:BL11,MATCH(2,1/(Données!C11:BL11<>""),0)-24+1),"") | H11: Banque de France
A12: Brent (USD/baril) | B12: USD | C12: =IFERROR(LOOKUP(2,1/(Données!C12:BL12<>""),Données!C12:BL12),"") -> 68.3 | D12: =IFERROR(LOOKUP(2,1/(Données!C12:BL12<>""),Données!C12:BL12)-INDEX(Données!C12:BL12,MATCH(2,1/(Données!C12:BL12<>""),0)-1+1),"") | E12: =IFERROR(LOOKUP(2,1/(Données!C12:BL12<>""),Données!C12:BL12)-INDEX(Données!C12:BL12,MATCH(2,1/(Données!C12:BL12<>""),0)-6+1),"") | F12: =IFERROR(LOOKUP(2,1/(Données!C12:BL12<>""),Données!C12:BL12)-INDEX(Données!C12:BL12,MATCH(2,1/(Données!C12:BL12<>""),0)-12+1),"") | G12: =IFERROR(LOOKUP(2,1/(Données!C12:BL12<>""),Données!C12:BL12)-INDEX(Données!C12:BL12,MATCH(2,1/(Données!C12:BL12<>""),0)-24+1),"") | H12: ICE / Bloomberg
A14: INDICATEURS ÉCONOMIQUES
A15: SMIC horaire brut | B15: € | C15: =IFERROR(LOOKUP(2,1/(Données!C15:BL15<>""),Données!C15:BL15),"") -> 11.88 | D15: =IFERROR(LOOKUP(2,1/(Données!C15:BL15<>""),Données!C15:BL15)-INDEX(Données!C15:BL15,MATCH(2,1/(Données!C15:BL15<>""),0)-1+1),"") | E15: =IFERROR(LOOKUP(2,1/(Données!C15:BL15<>""),Données!C15:BL15)-INDEX(Données!C15:BL15,MATCH(2,1/(Données!C15:BL15<>""),0)-6+1),"") | F15: =IFERROR(LOOKUP(2,1/(Données!C15:BL15<>""),Données!C15:BL15)-INDEX(Données!C15:BL15,MATCH(2,1/(Données!C15:BL15<>""),0)-12+1),"") | G15: =IFERROR(LOOKUP(2,1/(Données!C15:BL15<>""),Données!C15:BL15)-INDEX(Données!C15:BL15,MATCH(2,1/(Données!C15:BL15<>""),0)-24+1),"") | H15: Min. Travail
A16: Taux directeur BCE | B16: % | C16: =IFERROR(LOOKUP(2,1/(Données!C16:BL16<>""),Données!C16:BL16),"") -> 2.25 | D16: =IFERROR(LOOKUP(2,1/(Données!C16:BL16<>""),Données!C16:BL16)-INDEX(Données!C16:BL16,MATCH(2,1/(Données!C16:BL16<>""),0)-1+1),"") | E16: =IFERROR(LOOKUP(2,1/(Données!C16:BL16<>""),Données!C16:BL16)-INDEX(Données!C16:BL16,MATCH(2,1/(Données!C16:BL16<>""),0)-6+1),"") | F16: =IFERROR(LOOKUP(2,1/(Données!C16:BL16<>""),Données!C16:BL16)-INDEX(Données!C16:BL16,MATCH(2,1/(Données!C16:BL16<>""),0)-12+1),"") | G16: =IFERROR(LOOKUP(2,1/(Données!C16:BL16<>""),Données!C16:BL16)-INDEX(Données!C16:BL16,MATCH(2,1/(Données!C16:BL16<>""),0)-24+1),"") | H16: BCE
A17: Inflation France (IPC) | B17: % | C17: =IFERROR(LOOKUP(2,1/(Données!C17:BL17<>""),Données!C17:BL17),"") -> 0.7 | D17: =IFERROR(LOOKUP(2,1/(Données!C17:BL17<>""),Données!C17:BL17)-INDEX(Données!C17:BL17,MATCH(2,1/(Données!C17:BL17<>""),0)-1+1),"") | E17: =IFERROR(LOOKUP(2,1/(Données!C17:BL17<>""),Données!C17:BL17)-INDEX(Données!C17:BL17,MATCH(2,1/(Données!C17:BL17<>""),0)-6+1),"") | F17: =IFERROR(LOOKUP(2,1/(Données!C17:BL17<>""),Données!C17:BL17)-INDEX(Données!C17:BL17,MATCH(2,1/(Données!C17:BL17<>""),0)-12+1),"") | G17: =IFERROR(LOOKUP(2,1/(Données!C17:BL17<>""),Données!C17:BL17)-INDEX(Données!C17:BL17,MATCH(2,1/(Données!C17:BL17<>""),0)-24+1),"") | H17: INSEE
A18: Chômage France (BIT) | B18: % | C18: =IFERROR(LOOKUP(2,1/(Données!C18:BL18<>""),Données!C18:BL18),"") -> 7.3 | D18: =IFERROR(LOOKUP(2,1/(Données!C18:BL18<>""),Données!C18:BL18)-INDEX(Données!C18:BL18,MATCH(2,1/(Données!C18:BL18<>""),0)-1+1),"") | E18: =IFERROR(LOOKUP(2,1/(Données!C18:BL18<>""),Données!C18:BL18)-INDEX(Données!C18:BL18,MATCH(2,1/(Données!C18:BL18<>""),0)-6+1),"") | F18: =IFERROR(LOOKUP(2,1/(Données!C18:BL18<>""),Données!C18:BL18)-INDEX(Données!C18:BL18,MATCH(2,1/(Données!C18:BL18<>""),0)-12+1),"") | G18: =IFERROR(LOOKUP(2,1/(Données!C18:BL18<>""),Données!C18:BL18)-INDEX(Données!C18:BL18,MATCH(2,1/(Données!C18:BL18<>""),0)-24+1),"") | H18: INSEE
A19: Pass Navigo mensuel | B19: € | C19: =IFERROR(LOOKUP(2,1/(Données!C19:BL19<>""),Données!C19:BL19),"") -> 88.8 | D19: =IFERROR(LOOKUP(2,1/(Données!C19:BL19<>""),Données!C19:BL19)-INDEX(Données!C19:BL19,MATCH(2,1/(Données!C19:BL19<>""),0)-1+1),"") | E19: =IFERROR(LOOKUP(2,1/(Données!C19:BL19<>""),Données!C19:BL19)-INDEX(Données!C19:BL19,MATCH(2,1/(Données!C19:BL19<>""),0)-6+1),"") | F19: =IFERROR(LOOKUP(2,1/(Données!C19:BL19<>""),Données!C19:BL19)-INDEX(Données!C19:BL19,MATCH(2,1/(Données!C19:BL19<>""),0)-12+1),"") | G19: =IFERROR(LOOKUP(2,1/(Données!C19:BL19<>""),Données!C19:BL19)-INDEX(Données!C19:BL19,MATCH(2,1/(Données!C19:BL19<>""),0)-24+1),"") | H19: IDF Mobilités
A20: Baguette — prix moyen | B20: € | C20: =IFERROR(LOOKUP(2,1/(Données!C20:BL20<>""),Données!C20:BL20),"") -> 1.25 | D20: =IFERROR(LOOKUP(2,1/(Données!C20:BL20<>""),Données!C20:BL20)-INDEX(Données!C20:BL20,MATCH(2,1/(Données!C20:BL20<>""),0)-1+1),"") | E20: =IFERROR(LOOKUP(2,1/(Données!C20:BL20<>""),Données!C20:BL20)-INDEX(Données!C20:BL20,MATCH(2,1/(Données!C20:BL20<>""),0)-6+1),"") | F20: =IFERROR(LOOKUP(2,1/(Données!C20:BL20<>""),Données!C20:BL20)-INDEX(Données!C20:BL20,MATCH(2,1/(Données!C20:BL20<>""),0)-12+1),"") | G20: =IFERROR(LOOKUP(2,1/(Données!C20:BL20<>""),Données!C20:BL20)-INDEX(Données!C20:BL20,MATCH(2,1/(Données!C20:BL20<>""),0)-24+1),"") | H20: Fédération Boulangers
A21: Déficit public / PIB | B21: % PIB | C21: =IFERROR(LOOKUP(2,1/(Données!C21:BL21<>""),Données!C21:BL21),"") -> -5.8 | D21: =IFERROR(LOOKUP(2,1/(Données!C21:BL21<>""),Données!C21:BL21)-INDEX(Données!C21:BL21,MATCH(2,1/(Données!C21:BL21<>""),0)-1+1),"") | E21: =IFERROR(LOOKUP(2,1/(Données!C21:BL21<>""),Données!C21:BL21)-INDEX(Données!C21:BL21,MATCH(2,1/(Données!C21:BL21<>""),0)-6+1),"") | F21: =IFERROR(LOOKUP(2,1/(Données!C21:BL21<>""),Données!C21:BL21)-INDEX(Données!C21:BL21,MATCH(2,1/(Données!C21:BL21<>""),0)-12+1),"") | G21: =IFERROR(LOOKUP(2,1/(Données!C21:BL21<>""),Données!C21:BL21)-INDEX(Données!C21:BL21,MATCH(2,1/(Données!C21:BL21<>""),0)-24+1),"") | H21: INSEE / Eurostat
A22: Confiance ménages INSEE | B22: index | C22: =IFERROR(LOOKUP(2,1/(Données!C22:BL22<>""),Données!C22:BL22),"") -> 90 | D22: =IFERROR(LOOKUP(2,1/(Données!C22:BL22<>""),Données!C22:BL22)-INDEX(Données!C22:BL22,MATCH(2,1/(Données!C22:BL22<>""),0)-1+1),"") | E22: =IFERROR(LOOKUP(2,1/(Données!C22:BL22<>""),Données!C22:BL22)-INDEX(Données!C22:BL22,MATCH(2,1/(Données!C22:BL22<>""),0)-6+1),"") | F22: =IFERROR(LOOKUP(2,1/(Données!C22:BL22<>""),Données!C22:BL22)-INDEX(Données!C22:BL22,MATCH(2,1/(Données!C22:BL22<>""),0)-12+1),"") | G22: =IFERROR(LOOKUP(2,1/(Données!C22:BL22<>""),Données!C22:BL22)-INDEX(Données!C22:BL22,MATCH(2,1/(Données!C22:BL22<>""),0)-24+1),"") | H22: INSEE
A24: IMMOBILIER
A25: ICC — Coût Construction | B25: index | C25: =IFERROR(LOOKUP(2,1/(Données!C25:BL25<>""),Données!C25:BL25),"") -> 2058 | D25: =IFERROR(LOOKUP(2,1/(Données!C25:BL25<>""),Données!C25:BL25)-INDEX(Données!C25:BL25,MATCH(2,1/(Données!C25:BL25<>""),0)-1+1),"") | E25: =IFERROR(LOOKUP(2,1/(Données!C25:BL25<>""),Données!C25:BL25)-INDEX(Données!C25:BL25,MATCH(2,1/(Données!C25:BL25<>""),0)-6+1),"") | F25: =IFERROR(LOOKUP(2,1/(Données!C25:BL25<>""),Données!C25:BL25)-INDEX(Données!C25:BL25,MATCH(2,1/(Données!C25:BL25<>""),0)-12+1),"") | G25: =IFERROR(LOOKUP(2,1/(Données!C25:BL25<>""),Données!C25:BL25)-INDEX(Données!C25:BL25,MATCH(2,1/(Données!C25:BL25<>""),0)-24+1),"") | H25: INSEE
A26: ILC — Loyers Commerciaux | B26: index | C26: =IFERROR(LOOKUP(2,1/(Données!C26:BL26<>""),Données!C26:BL26),"") -> 134.62 | D26: =IFERROR(LOOKUP(2,1/(Données!C26:BL26<>""),Données!C26:BL26)-INDEX(Données!C26:BL26,MATCH(2,1/(Données!C26:BL26<>""),0)-1+1),"") | E26: =IFERROR(LOOKUP(2,1/(Données!C26:BL26<>""),Données!C26:BL26)-INDEX(Données!C26:BL26,MATCH(2,1/(Données!C26:BL26<>""),0)-6+1),"") | F26: =IFERROR(LOOKUP(2,1/(Données!C26:BL26<>""),Données!C26:BL26)-INDEX(Données!C26:BL26,MATCH(2,1/(Données!C26:BL26<>""),0)-12+1),"") | G26: =IFERROR(LOOKUP(2,1/(Données!C26:BL26<>""),Données!C26:BL26)-INDEX(Données!C26:BL26,MATCH(2,1/(Données!C26:BL26<>""),0)-24+1),"") | H26: INSEE
A27: ILAT — Act. Tertiaires | B27: index | C27: =IFERROR(LOOKUP(2,1/(Données!C27:BL27<>""),Données!C27:BL27),"") -> 137.21 | D27: =IFERROR(LOOKUP(2,1/(Données!C27:BL27<>""),Données!C27:BL27)-INDEX(Données!C27:BL27,MATCH(2,1/(Données!C27:BL27<>""),0)-1+1),"") | E27: =IFERROR(LOOKUP(2,1/(Données!C27:BL27<>""),Données!C27:BL27)-INDEX(Données!C27:BL27,MATCH(2,1/(Données!C27:BL27<>""),0)-6+1),"") | F27: =IFERROR(LOOKUP(2,1/(Données!C27:BL27<>""),Données!C27:BL27)-INDEX(Données!C27:BL27,MATCH(2,1/(Données!C27:BL27<>""),0)-12+1),"") | G27: =IFERROR(LOOKUP(2,1/(Données!C27:BL27<>""),Données!C27:BL27)-INDEX(Données!C27:BL27,MATCH(2,1/(Données!C27:BL27<>""),0)-24+1),"") | H27: INSEE
A28: IRL — Réf. des Loyers | B28: index | C28: =IFERROR(LOOKUP(2,1/(Données!C28:BL28<>""),Données!C28:BL28),"") -> 145.4 | D28: =IFERROR(LOOKUP(2,1/(Données!C28:BL28<>""),Données!C28:BL28)-INDEX(Données!C28:BL28,MATCH(2,1/(Données!C28:BL28<>""),0)-1+1),"") | E28: =IFERROR(LOOKUP(2,1/(Données!C28:BL28<>""),Données!C28:BL28)-INDEX(Données!C28:BL28,MATCH(2,1/(Données!C28:BL28<>""),0)-6+1),"") | F28: =IFERROR(LOOKUP(2,1/(Données!C28:BL28<>""),Données!C28:BL28)-INDEX(Données!C28:BL28,MATCH(2,1/(Données!C28:BL28<>""),0)-12+1),"") | G28: =IFERROR(LOOKUP(2,1/(Données!C28:BL28<>""),Données!C28:BL28)-INDEX(Données!C28:BL28,MATCH(2,1/(Données!C28:BL28<>""),0)-24+1),"") | H28: INSEE
A29: Taux crédit immo moyen | B29: % | C29: =IFERROR(LOOKUP(2,1/(Données!C29:BL29<>""),Données!C29:BL29),"") -> 2.88 | D29: =IFERROR(LOOKUP(2,1/(Données!C29:BL29<>""),Données!C29:BL29)-INDEX(Données!C29:BL29,MATCH(2,1/(Données!C29:BL29<>""),0)-1+1),"") | E29: =IFERROR(LOOKUP(2,1/(Données!C29:BL29<>""),Données!C29:BL29)-INDEX(Données!C29:BL29,MATCH(2,1/(Données!C29:BL29<>""),0)-6+1),"") | F29: =IFERROR(LOOKUP(2,1/(Données!C29:BL29<>""),Données!C29:BL29)-INDEX(Données!C29:BL29,MATCH(2,1/(Données!C29:BL29<>""),0)-12+1),"") | G29: =IFERROR(LOOKUP(2,1/(Données!C29:BL29<>""),Données!C29:BL29)-INDEX(Données!C29:BL29,MATCH(2,1/(Données!C29:BL29<>""),0)-24+1),"") | H29: Banque de France
A30: Transactions (12 mois) | B30: milliers | C30: =IFERROR(LOOKUP(2,1/(Données!C30:BL30<>""),Données!C30:BL30),"") -> 820 | D30: =IFERROR(LOOKUP(2,1/(Données!C30:BL30<>""),Données!C30:BL30)-INDEX(Données!C30:BL30,MATCH(2,1/(Données!C30:BL30<>""),0)-1+1),"") | E30: =IFERROR(LOOKUP(2,1/(Données!C30:BL30<>""),Données!C30:BL30)-INDEX(Données!C30:BL30,MATCH(2,1/(Données!C30:BL30<>""),0)-6+1),"") | F30: =IFERROR(LOOKUP(2,1/(Données!C30:BL30<>""),Données!C30:BL30)-INDEX(Données!C30:BL30,MATCH(2,1/(Données!C30:BL30<>""),0)-12+1),"") | G30: =IFERROR(LOOKUP(2,1/(Données!C30:BL30<>""),Données!C30:BL30)-INDEX(Données!C30:BL30,MATCH(2,1/(Données!C30:BL30<>""),0)-24+1),"") | H30: Notaires de France
A32: ÉNERGIE
A33: SMIC mensuel brut | B33: €/mois | C33: =IFERROR(LOOKUP(2,1/(Données!C36:BL36<>""),Données!C36:BL36),"") -> 1801.84 | D33: =IFERROR(LOOKUP(2,1/(Données!C36:BL36<>""),Données!C36:BL36)-INDEX(Données!C36:BL36,MATCH(2,1/(Données!C36:BL36<>""),0)-1+1),"") | E33: =IFERROR(LOOKUP(2,1/(Données!C36:BL36<>""),Données!C36:BL36)-INDEX(Données!C36:BL36,MATCH(2,1/(Données!C36:BL36<>""),0)-6+1),"") | F33: =IFERROR(LOOKUP(2,1/(Données!C36:BL36<>""),Données!C36:BL36)-INDEX(Données!C36:BL36,MATCH(2,1/(Données!C36:BL36<>""),0)-12+1),"") | G33: =IFERROR(LOOKUP(2,1/(Données!C36:BL36<>""),Données!C36:BL36)-INDEX(Données!C36:BL36,MATCH(2,1/(Données!C36:BL36<>""),0)-24+1),"") | H33: Calculé
A34: Tarif EDF réglementé | B34: €/kWh | C34: =IFERROR(LOOKUP(2,1/(Données!C37:BL37<>""),Données!C37:BL37),"") -> 0.2645 | D34: =IFERROR(LOOKUP(2,1/(Données!C37:BL37<>""),Données!C37:BL37)-INDEX(Données!C37:BL37,MATCH(2,1/(Données!C37:BL37<>""),0)-1+1),"") | E34: =IFERROR(LOOKUP(2,1/(Données!C37:BL37<>""),Données!C37:BL37)-INDEX(Données!C37:BL37,MATCH(2,1/(Données!C37:BL37<>""),0)-6+1),"") | F34: =IFERROR(LOOKUP(2,1/(Données!C37:BL37<>""),Données!C37:BL37)-INDEX(Données!C37:BL37,MATCH(2,1/(Données!C37:BL37<>""),0)-12+1),"") | G34: =IFERROR(LOOKUP(2,1/(Données!C37:BL37<>""),Données!C37:BL37)-INDEX(Données!C37:BL37,MATCH(2,1/(Données!C37:BL37<>""),0)-24+1),"") | H34: CRE / EDF
A35: Gaz naturel — prix réf. CRE | B35: €/MWh | C35: =IFERROR(LOOKUP(2,1/(Données!C38:BL38<>""),Données!C38:BL38),"") -> 60 | D35: =IFERROR(LOOKUP(2,1/(Données!C38:BL38<>""),Données!C38:BL38)-INDEX(Données!C38:BL38,MATCH(2,1/(Données!C38:BL38<>""),0)-1+1),"") | E35: =IFERROR(LOOKUP(2,1/(Données!C38:BL38<>""),Données!C38:BL38)-INDEX(Données!C38:BL38,MATCH(2,1/(Données!C38:BL38<>""),0)-6+1),"") | F35: =IFERROR(LOOKUP(2,1/(Données!C38:BL38<>""),Données!C38:BL38)-INDEX(Données!C38:BL38,MATCH(2,1/(Données!C38:BL38<>""),0)-12+1),"") | G35: =IFERROR(LOOKUP(2,1/(Données!C38:BL38<>""),Données!C38:BL38)-INDEX(Données!C38:BL38,MATCH(2,1/(Données!C38:BL38<>""),0)-24+1),"") | H35: CRE
A36: Taux Livret A | B36: % | C36: =IFERROR(LOOKUP(2,1/(Données!C39:BL39<>""),Données!C39:BL39),"") -> 1.7 | D36: =IFERROR(LOOKUP(2,1/(Données!C39:BL39<>""),Données!C39:BL39)-INDEX(Données!C39:BL39,MATCH(2,1/(Données!C39:BL39<>""),0)-1+1),"") | E36: =IFERROR(LOOKUP(2,1/(Données!C39:BL39<>""),Données!C39:BL39)-INDEX(Données!C39:BL39,MATCH(2,1/(Données!C39:BL39<>""),0)-6+1),"") | F36: =IFERROR(LOOKUP(2,1/(Données!C39:BL39<>""),Données!C39:BL39)-INDEX(Données!C39:BL39,MATCH(2,1/(Données!C39:BL39<>""),0)-12+1),"") | G36: =IFERROR(LOOKUP(2,1/(Données!C39:BL39<>""),Données!C39:BL39)-INDEX(Données!C39:BL39,MATCH(2,1/(Données!C39:BL39<>""),0)-24+1),"") | H36: Banque de France

Sheet Graphiques
A1: GRAPHIQUES — ÉVOLUTION PAR INDICATEUR
A2: Chaque graphique affiche les 60 derniers mois (5 ans). Pour zoomer sur 1 an, 6 mois ou 1 mois : sélectionnez le graphique et utilisez les poignées de l'axe horizontal.
A3: Période affichée : | C3: 5 ans (60 mois) | D3: 2 ans (24 mois) | E3: 1 an (12 mois) | F3: 6 mois | G3: 1 mois

Sheet Sources
A1: SOURCES ET INSTRUCTIONS DE SAISIE
A2: Indicateur | B2: Où trouver | C2: Quand saisir | D2: Note de lecture | E2: Lien
A3: MARCHÉS BOURSIERS
A4: CAC 40 | B4: Yahoo Finance / Google Finance | C4: 1er du mois | D4: Cours de clôture dernier jour ouvré du mois précédent | E4: Lien
A5: Euro Stoxx 50 | B5: Yahoo Finance | C5: 1er du mois | D5: Idem — cours de clôture | E5: Lien
A6: Nasdaq Composite | B6: Yahoo Finance | C6: 1er du mois | D6: Idem — cours de clôture | E6: Lien
A7: Dow Jones | B7: Yahoo Finance | C7: 1er du mois | D7: Idem — cours de clôture | E7: Lien
A8: VIX | B8: Yahoo Finance / CBOE | C8: 1er du mois | D8: <15 calme, 15-25 incertitude, >30 peur | E8: Lien
A9: EUR / USD | B9: Yahoo Finance | C9: 1er du mois | D9: Cours de clôture dernier jour ouvré | E9: Lien
A10: OAT 10 ans | B10: Banque de France Webstat | C10: 1er du mois | D10: Taux souverain fr. 10 ans — corrélé aux taux crédit immo | E10: Lien
A11: Brent | B11: Yahoo Finance (BZ=F) | C11: 1er du mois | D11: Contrat futur ICE, en USD | E11: Lien
A12: ÉCONOMIQUE
A13: SMIC horaire brut | B13: service-public.fr | C13: À chaque revalorisation | D13: Revalorisations habituellement au 1er janvier et 1er mai | E13: Lien
A14: Taux directeur BCE | B14: Site BCE | C14: À chaque décision (~6 sem.) | D14: Taux de dépôt. Reporter la valeur sur tous les mois sans changement | E14: Lien
A15: Inflation (IPC) | B15: INSEE — série 001759970 | C15: Mensuel (publication J+20) | D15: Glissement annuel en % | E15: Lien
A16: Chômage France | B16: INSEE — série 001688526 | C16: Trimestriel | D16: Taux BIT France métrop. Reporter sur les 3 mois du trimestre | E16: Lien
A17: Pass Navigo | B17: IDF Mobilités | C17: Annuel (janvier) | D17: Tarif toutes zones. Augmentation début janvier | E17: Lien
A18: Baguette | B18: Fédération des Boulangers / presse | C18: Annuel (approx.) | D18: Prix moyen constaté — pas de prix réglementé national | E18: Lien
A19: Déficit public/PIB | B19: INSEE / Eurostat | C19: Annuel (mars-avril N+1) | D19: Notification Eurostat publiée en mars/avril de l'année suivante | E19: Lien
A20: Confiance ménages | B20: INSEE — série 001605612 | C20: Mensuel (fin de mois) | D20: Index synthétique. Base 100 = moyenne long terme. <100 = pessimisme | E20: Lien
A21: IMMOBILIER
A22: ICC | B22: INSEE — série 000868550 | C22: Trimestriel +3 mois | D22: Reporter la même valeur sur les 3 mois du trimestre | E22: Lien
A23: ILC | B23: INSEE — série 001515769 | C23: Trimestriel +3 mois | D23: Base 100 = T1 2008. Plafonne les révisions loyers commerciaux | E23: Lien
A24: ILAT | B24: INSEE — série 001515770 | C24: Trimestriel +3 mois | D24: Base 100 = T1 2010. Loyers activités tertiaires | E24: Lien
A25: IRL | B25: INSEE — série 001515766 | C25: Trimestriel +3 mois | D25: Base 100 = T4 2005. Plafonne les révisions loyers résidentiels | E25: Lien
A26: Taux crédit immo | B26: Banque de France Webstat ou Meilleurtaux | C26: Mensuel | D26: Taux moyen toutes durées nouveaux contrats | E26: Lien
A27: Transactions logements | B27: Notaires de France | C27: Trimestriel | D27: Cumul 12 mois glissants en milliers | E27: Lien
